pyams_site/__init__.py
pyams_site/include.py
pyams_site/interfaces.py
pyams_site/site.py
pyams_site/doctests/README.rst
pyams_site/generations/__init__.py
pyams_site/generations/timezone.py
pyams_site/generations/zodbupdate.py
pyams_site/locales/pyams_site.pot
pyams_site/locales/fr/LC_MESSAGES/pyams_site.po
pyams_site/scripts/__init__.py
pyams_site/tests/__init__.py
pyams_site/tests/test_utilsdocs.py
pyams_site/tests/test_utilsdocstrings.py
pyams_site-2.0.1.dist-info/LICENSE
pyams_site-2.0.1.dist-info/METADATA
pyams_site-2.0.1.dist-info/WHEEL
pyams_site-2.0.1.dist-info/entry_points.txt
pyams_site-2.0.1.dist-info/namespace_packages.txt
pyams_site-2.0.1.dist-info/top_level.txt
pyams_site-2.0.1.dist-info/RECORD
