Metadata-Version: 2.1
Name: pyams-site
Version: 2.0.1
Summary: PyAMS site management features
Home-page: https://pyams.readthedocs.io
Author: Thierry Florac
Author-email: tflorac@ulthar.net
License: ZPL
Keywords: Pyramid PyAMS
Classifier: License :: OSI Approved :: Zope Public License
Classifier: Development Status :: 4 - Beta
Classifier: Programming Language :: Python
Classifier: Framework :: Pyramid
Classifier: Topic :: Software Development :: Libraries :: Python Modules
Requires-Python: >=3.7
License-File: LICENSE
Requires-Dist: setuptools
Requires-Dist: persistent
Requires-Dist: pyams-utils
Requires-Dist: pyramid >=2.0.0
Requires-Dist: pyramid-zodbconn
Requires-Dist: transaction
Requires-Dist: zodbupdate
Requires-Dist: zope.annotation
Requires-Dist: zope.component
Requires-Dist: zope.interface
Requires-Dist: zope.lifecycleevent
Requires-Dist: zope.site
Requires-Dist: zope.traversing
Provides-Extra: test
